MANIFEST.in
README.rst
semigroups.cpp
semigroups.pyx
semigroups_cpp.cpp
semigroups_cpp.h
semigroups_cpp.pxd
setup.cfg
setup.py
.eggs/README.txt
.eggs/pytest_cython-0.1.0-py2.7.egg/EGG-INFO/SOURCES.txt
.eggs/pytest_cython-0.1.0-py2.7.egg/EGG-INFO/dependency_links.txt
.eggs/pytest_cython-0.1.0-py2.7.egg/EGG-INFO/entry_points.txt
.eggs/pytest_cython-0.1.0-py2.7.egg/EGG-INFO/requires.txt
.eggs/pytest_cython-0.1.0-py2.7.egg/EGG-INFO/top_level.txt
libsemigroups_python_bindings.egg-info/PKG-INFO
libsemigroups_python_bindings.egg-info/SOURCES.txt
libsemigroups_python_bindings.egg-info/dependency_links.txt
libsemigroups_python_bindings.egg-info/top_level.txt