Metadata-Version: 1.1
Name: libsemigroups-python-bindings
Version: 0.2.2
Summary: Python bindings for the libsemigroups mathematics library
Home-page: https://github.com/james-d-mitchell/libsemigroups/tree/master/python-bindings
Author: James Mitchell and Nicolas M. Thiéry
Author-email: TODO
License: GPLv3
Keywords: Mathematics,semigroup theory
Platform: UNKNOWN
Classifier: Development Status :: 3 - Alpha
Classifier: Intended Audience :: Developers
Classifier: Intended Audience :: Science/Research
Classifier: Topic :: Scientific/Engineering :: Mathematics
Classifier: License :: OSI Approved :: GNU General Public License v3 (GPLv3)
Classifier: Programming Language :: Python :: 2
Classifier: Programming Language :: Python :: 3
